quantune/__init__.py
quantune/algorithms/VQE.py
quantune/algorithms/__init__.py
quantune/backends/Simulator.py
quantune/backends/__init__.py
quantune/core/Calculator.py
quantune/core/__init__.py
quantune/core/quantum_state.py
quantune/core/circuit_visualizer/__init__.py
quantune/core/circuit_visualizer/visual.py
quantune/core/quantum_circuit/Calculator.py
quantune/core/quantum_circuit/__init__.py
quantune/core/quantum_circuit/quantum_circuit.py
quantune/core/quantum_circuit/base/__init__.py
quantune/core/quantum_circuit/base/base_calculator.py
quantune/core/quantum_circuit/gpu/__init__.py
quantune/core/quantum_circuit/gpu/gpu_calculator.py
quantune/core/quantum_circuit/interface/__init__.py
quantune/core/quantum_circuit/interface/calculator_interface.py
quantune/core/quantum_circuit/operations/__init__.py
quantune/core/quantum_gate/__init__.py
quantune/core/quantum_gate/gates.py
quantune/core/qubit/__init__.py
quantune/core/qubit/quantum_register.py
quantune/core/qubit/qubit.py
quantune/core/tools/__init__.py
quantune/core/tools/amplitude.py
quantune/core/tools/measure.py
quantune/core/tools/phase_angle.py
quantune/core/tools/probability.py
quantune/core/tools/base/__init__.py
quantune/core/tools/base/convert_state.py
quantune/tests/__init__.py
quantune/tests/dev_test1.py
quantune/tests/test_quantum_circuit.py
qumega-0.0.1.dist-info/LICENSE
qumega-0.0.1.dist-info/METADATA
qumega-0.0.1.dist-info/WHEEL
qumega-0.0.1.dist-info/top_level.txt
qumega-0.0.1.dist-info/RECORD
