Metadata-Version: 2.1
Name: qumega
Version: 0.0.1
Summary: Qumega is a powerful and versatile library for quantum computing, developed by NeoCosmicX.
Home-page: https://github.com/Neocosmicx-Quantum/Quantune
Author: Neocosmicx
Author-email: sejanbagani14@gmail.com
License: Apache License 2.0
Classifier: Intended Audience :: Developers
Classifier: Operating System :: OS Independent
Classifier: License :: OSI Approved :: Apache Software License
Requires-Python: >=3.12
License-File: LICENSE
Requires-Dist: matplotlib>=3.10.0
Requires-Dist: numpy>=2.2.1
Requires-Dist: setuptools>=75.8.0
Requires-Dist: scipy>=1.15.1
Requires-Dist: pytest>=8.3.4
Requires-Dist: black>=24.10.0
Requires-Dist: pillow>=11.1.0
Requires-Dist: pyparsing>=3.2.1
Requires-Dist: python-dateutil>=2.9.0.post0
Requires-Dist: scipy>=1.15.1
Requires-Dist: six>=1.17.0
Requires-Dist: cupy-cuda12x>=13.3.0
